{
    "sheets": [
        {
            "sheet1": {
                "table": [
                    "<input type=\"text\" id=\"A1\" class=\"\" value=\"name\">",
                    "<input type=\"text\" id=\"B1\" class=\"\" value=\"age\">",
                    "<input type=\"text\" id=\"C1\" class=\"\" value=\"mark\">",
                    "<input type=\"text\" id=\"D1\" class=\"\" value=\"math\">",
                    "<input type=\"text\" id=\"A2\" class=\"\" value=\"hazemof\">",
                    "<input type=\"text\" id=\"B2\" class=\"\" selected-index=\"1\" value=\"21\">",
                    "<input type=\"text\" id=\"C2\" class=\"\" selected-index=\"2\" value=\"60\">",
                    "<input type=\"text\" id=\"D2\" class=\"\" value=\"12\">",
                    "<input type=\"text\" id=\"A3\" class=\"\" selected-index=\"1\" value=\"ahmadof\">",
                    "<input type=\"text\" id=\"B3\" class=\"\" selected-index=\"1\" value=\"22\">",
                    "<input type=\"text\" id=\"C3\" class=\"\" selected-index=\"1\" value=\"70\">",
                    "<input type=\"text\" id=\"D3\" class=\"\" value=\"90\">",
                    "<input type=\"text\" id=\"A4\" class=\"\" selected-index=\"1\" value=\"areejof\">",
                    "<input type=\"text\" id=\"B4\" class=\"\" selected-index=\"1\" value=\"23\">",
                    "<input type=\"text\" id=\"C4\" class=\"\" selected-index=\"3\" value=\"40\">",
                    "<input type=\"text\" id=\"D4\" class=\"\" value=\"30\">",
                    "<input type=\"text\" id=\"A5\" class=\"\" selected-index=\"1\" value=\"ammar\">",
                    "<input type=\"text\" id=\"B5\" class=\"\" selected-index=\"1\" value=\"21\">",
                    "<input type=\"text\" id=\"C5\" class=\"\" value=\"50\">",
                    "<input type=\"text\" id=\"D5\" class=\"\" value=\"80\">",
                    "<input type=\"text\" id=\"A6\" class=\"\" selected-index=\"1\" value=\"thsenof\">",
                    "<input type=\"text\" id=\"B6\" class=\"\" selected-index=\"1\" value=\"22\">",
                    "<input type=\"text\" id=\"C6\" class=\"\" value=\"40\">",
                    "<input type=\"text\" id=\"D6\" class=\"\" value=\"70\">",
                    "<input type=\"text\" id=\"A7\" class=\"\" selected-index=\"2\" value=\"ahsan\">",
                    "<input type=\"text\" id=\"B7\" class=\"\" selected-index=\"1\" value=\"24\">",
                    "<input type=\"text\" id=\"C7\" class=\"\" value=\"90\">",
                    "<input type=\"text\" id=\"D7\" class=\"\" value=\"60\">",
                    "<input type=\"text\" id=\"A8\" class=\"\" selected-index=\"1\" value=\"aslam\">",
                    "<input type=\"text\" id=\"B8\" class=\"\" selected-index=\"1\" value=\"22\">",
                    "<input type=\"text\" id=\"C8\" class=\"\" value=\"40\">",
                    "<input type=\"text\" id=\"D8\" class=\"\" value=\"50\">",
                    "<input type=\"text\" id=\"A9\" class=\"\" selected-index=\"3\" value=\"omaran\">",
                    "<input type=\"text\" id=\"B9\" class=\"\" selected-index=\"1\" value=\"23\">",
                    "<input type=\"text\" id=\"C9\" class=\"\" value=\"20\">",
                    "<input type=\"text\" id=\"D9\" class=\"\" value=\"12\">",
                    "<input type=\"text\" id=\"A10\" class=\"\" value=\"areejof\">",
                    "<input type=\"text\" id=\"B10\" class=\"\" selected-index=\"1\" value=\"23\">",
                    "<input type=\"text\" id=\"C10\" class=\"\" value=\"0\">",
                    "<input type=\"text\" id=\"A11\" class=\"\" value=\"areejof\">",
                    "<input type=\"text\" id=\"B11\" class=\"\" value=\"23\">",
                    "<input type=\"text\" id=\"C11\" class=\"\" value=\"22\">",
                    "<input type=\"text\" id=\"A12\" class=\"\" value=\"areejof\">",
                    "<input type=\"text\" id=\"B12\" class=\"\" selected-index=\"1\" value=\"23\">",
                    "<input type=\"text\" id=\"C12\" class=\"\" value=\"22\">",
                    "<input type=\"text\" id=\"A13\" class=\"\" value=\"areejof\">",
                    "<input type=\"text\" id=\"B13\" class=\"\" value=\"23\">",
                    "<input type=\"text\" id=\"C13\" class=\"\" value=\"22\">",
                    "<input type=\"text\" id=\"A14\" class=\"\" selected-index=\"1\" value=\"areejof\">",
                    "<input type=\"text\" id=\"B14\" class=\"\" selected-index=\"1\" value=\"23\">",
                    "<input type=\"text\" id=\"C14\" class=\"selected\" value=\"22\">"
                ],
                "richtext": "",
                "maxcol": "30",
                "maxrow": "30"
            }
        }
    ]
}